emapper2gbk/__init__.py
emapper2gbk/__main__.py
emapper2gbk/emapper2gbk.py
emapper2gbk/genes_to_gbk.py
emapper2gbk/genomes_to_gbk.py
emapper2gbk/utils.py
emapper2gbk-0.3.2.dist-info/licenses/AUTHORS.rst
emapper2gbk-0.3.2.dist-info/licenses/LICENSE
emapper2gbk-0.3.2.dist-info/METADATA
emapper2gbk-0.3.2.dist-info/WHEEL
emapper2gbk-0.3.2.dist-info/entry_points.txt
emapper2gbk-0.3.2.dist-info/top_level.txt
emapper2gbk-0.3.2.dist-info/RECORD
