Metadata-Version: 2.4
Name: emapper2gbk
Version: 0.3.2
Summary: Build .gbk files starting from eggnog annotation files and genomes (fasta)
Author-email: AuReMe <gem-aureme@inria.fr>
License: LGPL-3.0-or-later
Project-URL: Homepage, https://github.com/AuReMe/emapper2gbk
Project-URL: Changelog, https://github.com/AuReMe/emapper2gbk/blob/main/CHANGELOG.md
Classifier: Development Status :: 2 - Pre-Alpha
Classifier: Intended Audience :: Developers
Classifier: License :: OSI Approved :: GNU Lesser General Public License v3 or later (LGPLv3+)
Classifier: Natural Language :: English
Classifier: Programming Language :: Python :: 3.9
License-File: LICENSE
License-File: AUTHORS.rst
Requires-Dist: biopython
Requires-Dist: ete4
Requires-Dist: gffutils
Requires-Dist: pandas
Requires-Dist: pronto
Requires-Dist: requests
Dynamic: license-file
